LICENSE
README.md
setup.cfg
setup.py
meow_sms/__init__.py
meow_sms/meowsms.py
meow_sms.egg-info/PKG-INFO
meow_sms.egg-info/SOURCES.txt
meow_sms.egg-info/dependency_links.txt
meow_sms.egg-info/not-zip-safe
meow_sms.egg-info/requires.txt
meow_sms.egg-info/top_level.txt
meow_sms/models/__init__.py
meow_sms/models/countries.py
meow_sms/models/domain.py
meow_sms/models/profile.py
meow_sms/models/send.py
meow_sms/models/services.py